{
  "task_id": "6f6da5ef5df2d0a34368bcad9befa3e6",
  "status": "error",
  "created_at": "2025-05-23T10:13:34.606408",
  "last_update": "2025-05-23T10:13:34.606408",
  "callback_received": true,
  "callback_data": {
    "callbackType": "complete",
    "task_id": "6f6da5ef5df2d0a34368bcad9befa3e6"
  },
  "error": "Internal Error, Please try again later.",
  "last_callback": {
    "code": 500,
    "data": {
      "callbackType": "complete",
      "task_id": "6f6da5ef5df2d0a34368bcad9befa3e6"
    },
    "msg": "Internal Error, Please try again later."
  }
}